rezka_api_sdk/__init__.py
rezka_api_sdk/constants.py
rezka_api_sdk/enums.py
rezka_api_sdk/exceptions.py
rezka_api_sdk/models.py
rezka_api_sdk/rezka_api.py
rezka_api_sdk-0.1.0.dist-info/METADATA
rezka_api_sdk-0.1.0.dist-info/WHEEL
rezka_api_sdk-0.1.0.dist-info/RECORD
