Metadata-Version: 2.3
Name: rezka-api-sdk
Version: 0.1.0
Summary: It is a library that allows you to interact with unofficial HDRezka API
Keywords: rezka,hdrezka,films,series
Author: Aryn Yklas
Author-email: arynyklas@gmail.com
Requires-Python: >=3.10
Classifier: Programming Language :: Python
Classifier: Programming Language :: Python :: 3
Classifier: Programming Language :: Python :: 3.10
Requires-Dist: httpx (>=0.28.1,<0.29.0)
Requires-Dist: pydantic (>=2.10.6,<3.0.0)
Project-URL: Homepage, https://github.com/arynyklas/rezka_api_sdk
Project-URL: Repository, https://github.com/arynyklas/rezka_api_sdk
Project-URL: github, https://github.com/arynyklas/rezka_api_sdk
Project-URL: source, https://github.com/arynyklas/rezka_api_sdk
